{"ville":{"id":2022,"code_insee":"27133","nom_standard":"Caumont","nom_a":null,"nom_de":null,"slug_ville":"caumont","departement_id":628,"code_postal":"27310","population":1109,"superficie_km2":"6.00","latitude_centre":"49.3670006","longitude_centre":"0.9080000","dep_code":"27","dep_nom":"Eure","dep_slug":"eure","reg_code":"14","reg_nom":"Normandie","reg_slug":"normandie"},"departement":{"code":"27","nom":"Eure","slug":"eure"},"region":{"code":"14","nom":"Normandie","slug":"normandie"},"villes_proches":[{"id":2100,"code_insee":"27580","nom_standard":"Saint-Ouen-de-Thouberville","nom_a":null,"nom_de":null,"slug_ville":"saint-ouen-de-thouberville","departement_id":628,"code_postal":"27310","population":2446,"superficie_km2":"6.00","latitude_centre":"49.3489990","longitude_centre":"0.8960000","distance_km":2.18},{"id":8033,"code_insee":"76550","nom_standard":"Sahurs","nom_a":null,"nom_de":null,"slug_ville":"sahurs","departement_id":677,"code_postal":"76113","population":1219,"superficie_km2":"11.00","latitude_centre":"49.3670006","longitude_centre":"0.9490000","distance_km":2.97},{"id":7989,"code_insee":"76391","nom_standard":"La Londe","nom_a":null,"nom_de":null,"slug_ville":"la-londe","departement_id":677,"code_postal":"76500","population":2362,"superficie_km2":"31.00","latitude_centre":"49.3240013","longitude_centre":"0.9200000","distance_km":4.86},{"id":7971,"code_insee":"76319","nom_standard":"Grand-Couronne","nom_a":null,"nom_de":null,"slug_ville":"grand-couronne","departement_id":677,"code_postal":"76530","population":9726,"superficie_km2":"17.00","latitude_centre":"49.3479996","longitude_centre":"1.0050000","distance_km":7.34},{"id":2013,"code_insee":"27103","nom_standard":"Bourg-Achard","nom_a":null,"nom_de":null,"slug_ville":"bourg-achard","departement_id":628,"code_postal":"27310","population":4014,"superficie_km2":"12.00","latitude_centre":"49.3450012","longitude_centre":"0.8090000","distance_km":7.58},{"id":2014,"code_insee":"27105","nom_standard":"Grand Bourgtheroulde","nom_a":null,"nom_de":null,"slug_ville":"grand-bourgtheroulde","departement_id":628,"code_postal":"27520","population":4025,"superficie_km2":"12.00","latitude_centre":"49.2999992","longitude_centre":"0.8760000","distance_km":7.8},{"id":2101,"code_insee":"27582","nom_standard":"Saint-Ouen-du-Tilleul","nom_a":null,"nom_de":null,"slug_ville":"saint-ouen-du-tilleul","departement_id":628,"code_postal":"27670","population":1762,"superficie_km2":"4.00","latitude_centre":"49.3009987","longitude_centre":"0.9450000","distance_km":7.81},{"id":2010,"code_insee":"27090","nom_standard":"Bosroumois","nom_a":null,"nom_de":null,"slug_ville":"bosroumois","departement_id":628,"code_postal":"27670","population":3786,"superficie_km2":"10.00","latitude_centre":"49.2929993","longitude_centre":"0.9220000","distance_km":8.29},{"id":7984,"code_insee":"76378","nom_standard":"Jumièges","nom_a":null,"nom_de":null,"slug_ville":"jumieges","departement_id":677,"code_postal":"76480","population":1726,"superficie_km2":"19.00","latitude_centre":"49.4269981","longitude_centre":"0.8320000","distance_km":8.65},{"id":2008,"code_insee":"27085","nom_standard":"Flancourt-Crescy-en-Roumois","nom_a":null,"nom_de":null,"slug_ville":"flancourt-crescy-en-roumois","departement_id":628,"code_postal":"27310","population":1569,"superficie_km2":"4.00","latitude_centre":"49.3170013","longitude_centre":"0.8070000","distance_km":9.19},{"id":8019,"code_insee":"76497","nom_standard":"Petit-Couronne","nom_a":null,"nom_de":null,"slug_ville":"petit-couronne","departement_id":677,"code_postal":"76650","population":8688,"superficie_km2":"13.00","latitude_centre":"49.3810005","longitude_centre":"1.0340000","distance_km":9.25},{"id":7903,"code_insee":"76020","nom_standard":"Anneville-Ambourville","nom_a":null,"nom_de":null,"slug_ville":"anneville-ambourville","departement_id":677,"code_postal":"76480","population":1168,"superficie_km2":"20.00","latitude_centre":"49.4500008","longitude_centre":"0.8920000","distance_km":9.3},{"id":8052,"code_insee":"76614","nom_standard":"Saint-Martin-de-Boscherville","nom_a":null,"nom_de":null,"slug_ville":"saint-martin-de-boscherville","departement_id":677,"code_postal":"76840","population":1541,"superficie_km2":"13.00","latitude_centre":"49.4449997","longitude_centre":"0.9630000","distance_km":9.54},{"id":2002,"code_insee":"27062","nom_standard":"Les Monts du Roumois","nom_a":null,"nom_de":null,"slug_ville":"les-monts-du-roumois","departement_id":628,"code_postal":"27370","population":1571,"superficie_km2":"9.00","latitude_centre":"49.2949982","longitude_centre":"0.8280000","distance_km":9.88},{"id":2012,"code_insee":"27102","nom_standard":"Bouquetot","nom_a":null,"nom_de":null,"slug_ville":"bouquetot","departement_id":628,"code_postal":"27310","population":1027,"superficie_km2":"13.00","latitude_centre":"49.3610001","longitude_centre":"0.7700000","distance_km":10.02},{"id":7928,"code_insee":"76157","nom_standard":"Canteleu","nom_a":null,"nom_de":null,"slug_ville":"canteleu","departement_id":677,"code_postal":"76380","population":13966,"superficie_km2":"18.00","latitude_centre":"49.4329987","longitude_centre":"1.0140001","distance_km":10.62},{"id":7973,"code_insee":"76322","nom_standard":"Le Grand-Quevilly","nom_a":null,"nom_de":null,"slug_ville":"le-grand-quevilly","departement_id":677,"code_postal":"76120","population":25975,"superficie_km2":"11.00","latitude_centre":"49.4090004","longitude_centre":"1.0400000","distance_km":10.63},{"id":8039,"code_insee":"76561","nom_standard":"Saint-Aubin-lès-Elbeuf","nom_a":null,"nom_de":null,"slug_ville":"saint-aubin-les-elbeuf","departement_id":677,"code_postal":"76410","population":8428,"superficie_km2":"6.00","latitude_centre":"49.3030014","longitude_centre":"1.0180000","distance_km":10.69},{"id":2057,"code_insee":"27316","nom_standard":"Hauville","nom_a":null,"nom_de":null,"slug_ville":"hauville","departement_id":628,"code_postal":"27350","population":1294,"superficie_km2":"15.00","latitude_centre":"49.3969994","longitude_centre":"0.7670000","distance_km":10.74},{"id":7934,"code_insee":"76178","nom_standard":"Cléon","nom_a":null,"nom_de":null,"slug_ville":"cleon","departement_id":677,"code_postal":"76410","population":4907,"superficie_km2":"6.00","latitude_centre":"49.3160019","longitude_centre":"1.0400000","distance_km":11.12}]}