{"ville":{"id":30985,"code_insee":"71509","nom_standard":"La Celle-en-Morvan","nom_a":null,"nom_de":null,"slug_ville":"la-celle-en-morvan","departement_id":0,"code_postal":"71400","population":452,"superficie_km2":"2017.51","latitude_centre":"47.0079","longitude_centre":"4.1717","dep_code":"71","dep_nom":"Saône-et-Loire","dep_slug":"saone-et-loire","reg_code":"27","reg_nom":"Bourgogne-Franche-Comté","reg_slug":"bourgogne-franche-comte"},"departement":{"code":"71","nom":"Saône-et-Loire","slug":"saone-et-loire"},"region":{"code":"27","nom":"Bourgogne-Franche-Comté","slug":"bourgogne-franche-comte"},"villes_proches":[{"id":30862,"code_insee":"71349","nom_standard":"La Petite-Verrière","nom_a":null,"nom_de":null,"slug_ville":"la-petite-verriere","departement_id":0,"code_postal":"71400","population":47,"superficie_km2":"982.91","latitude_centre":"47.0454","longitude_centre":"4.1681","distance_km":4.18},{"id":30763,"code_insee":"71223","nom_standard":"La Grande-Verrière","nom_a":null,"nom_de":null,"slug_ville":"la-grande-verriere","departement_id":0,"code_postal":"71990","population":542,"superficie_km2":"4662.94","latitude_centre":"46.9699","longitude_centre":"4.1425","distance_km":4.77},{"id":0,"code_insee":"71535","nom_standard":"Tavernay","nom_a":null,"nom_de":null,"slug_ville":"tavernay","departement_id":0,"code_postal":"71400","population":493,"superficie_km2":"2579.56","latitude_centre":"47.0078","longitude_centre":"4.2363","distance_km":4.9},{"id":30883,"code_insee":"71376","nom_standard":"Roussillon-en-Morvan","nom_a":null,"nom_de":null,"slug_ville":"roussillon-en-morvan","departement_id":0,"code_postal":"71550","population":272,"superficie_km2":"3058.10","latitude_centre":"47.0213","longitude_centre":"4.0998","distance_km":5.65},{"id":0,"code_insee":"71527","nom_standard":"Sommant","nom_a":null,"nom_de":null,"slug_ville":"sommant","departement_id":0,"code_postal":"71540","population":184,"superficie_km2":"2058.20","latitude_centre":"47.0571","longitude_centre":"4.2138","distance_km":6.33},{"id":30833,"code_insee":"71313","nom_standard":"Monthelon","nom_a":null,"nom_de":null,"slug_ville":"monthelon","departement_id":0,"code_postal":"71400","population":367,"superficie_km2":"2469.26","latitude_centre":"46.9596","longitude_centre":"4.2224","distance_km":6.61},{"id":30916,"code_insee":"71414","nom_standard":"Saint-Forgeot","nom_a":null,"nom_de":null,"slug_ville":"saint-forgeot","departement_id":0,"code_postal":"71400","population":435,"superficie_km2":"1607.03","latitude_centre":"47","longitude_centre":"4.2872","distance_km":8.8},{"id":30598,"code_insee":"71009","nom_standard":"Anost","nom_a":null,"nom_de":null,"slug_ville":"anost","departement_id":0,"code_postal":"71550","population":695,"superficie_km2":"5190.91","latitude_centre":"47.0788","longitude_centre":"4.0977","distance_km":9.67},{"id":30879,"code_insee":"71368","nom_standard":"Reclesne","nom_a":null,"nom_de":null,"slug_ville":"reclesne","departement_id":0,"code_postal":"71540","population":289,"superficie_km2":"2094.22","latitude_centre":"47.0483","longitude_centre":"4.2848","distance_km":9.68},{"id":30720,"code_insee":"71165","nom_standard":"Cussy-en-Morvan","nom_a":null,"nom_de":null,"slug_ville":"cussy-en-morvan","departement_id":0,"code_postal":"71550","population":346,"superficie_km2":"3499.11","latitude_centre":"47.0955","longitude_centre":"4.173","distance_km":9.74},{"id":30961,"code_insee":"71472","nom_standard":"Saint-Prix","nom_a":null,"nom_de":null,"slug_ville":"saint-prix","departement_id":0,"code_postal":"71990","population":201,"superficie_km2":"3418.13","latitude_centre":"46.9703","longitude_centre":"4.0486","distance_km":10.23},{"id":30788,"code_insee":"71251","nom_standard":"Laizy","nom_a":null,"nom_de":null,"slug_ville":"laizy","departement_id":0,"code_postal":"71190","population":599,"superficie_km2":"3125.92","latitude_centre":"46.9135","longitude_centre":"4.1849","distance_km":10.54},{"id":30800,"code_insee":"71266","nom_standard":"Lucenay-l'Évêque","nom_a":null,"nom_de":null,"slug_ville":"lucenay-l-eveque","departement_id":0,"code_postal":"71540","population":333,"superficie_km2":"2536.51","latitude_centre":"47.0828","longitude_centre":"4.2614","distance_km":10.75},{"id":30642,"code_insee":"71062","nom_standard":"Brion","nom_a":null,"nom_de":null,"slug_ville":"brion","departement_id":0,"code_postal":"71190","population":303,"superficie_km2":"1667.13","latitude_centre":"46.9167","longitude_centre":"4.2392","distance_km":11.36},{"id":30936,"code_insee":"71440","nom_standard":"Saint-Léger-sous-Beuvray","nom_a":null,"nom_de":null,"slug_ville":"saint-leger-sous-beuvray","departement_id":0,"code_postal":"71990","population":369,"superficie_km2":"3508.77","latitude_centre":"46.919","longitude_centre":"4.0928","distance_km":11.56},{"id":0,"code_insee":"71014","nom_standard":"Autun","nom_a":null,"nom_de":null,"slug_ville":"autun","departement_id":0,"code_postal":"71400","population":13172,"superficie_km2":"6173.08","latitude_centre":"46.9386","longitude_centre":"4.3038","distance_km":12.64},{"id":30696,"code_insee":"71129","nom_standard":"Chissey-en-Morvan","nom_a":null,"nom_de":null,"slug_ville":"chissey-en-morvan","departement_id":0,"code_postal":"71540","population":308,"superficie_km2":"2995.05","latitude_centre":"47.1212","longitude_centre":"4.2138","distance_km":13.0},{"id":15532,"code_insee":"21403","nom_standard":"Ménessaire","nom_a":null,"nom_de":null,"slug_ville":"menessaire","departement_id":0,"code_postal":"21430","population":75,"superficie_km2":"1506.56","latitude_centre":"47.1326","longitude_centre":"4.149","distance_km":13.97},{"id":30704,"code_insee":"71142","nom_standard":"La Comelle","nom_a":null,"nom_de":null,"slug_ville":"la-comelle","departement_id":0,"code_postal":"71990","population":248,"superficie_km2":"2274.52","latitude_centre":"46.8771","longitude_centre":"4.1192","distance_km":15.08},{"id":0,"code_insee":"71192","nom_standard":"Étang-sur-Arroux","nom_a":null,"nom_de":null,"slug_ville":"etang-sur-arroux","departement_id":0,"code_postal":"71190","population":1750,"superficie_km2":"3459.26","latitude_centre":"46.8622","longitude_centre":"4.1832","distance_km":16.22}]}