{"ville":{"id":12671,"code_insee":"10196","nom_standard":"Lignières","nom_a":null,"nom_de":null,"slug_ville":"lignieres","departement_id":0,"code_postal":"10130","population":223,"superficie_km2":"2594.17","latitude_centre":"47.9635","longitude_centre":"3.967","dep_code":"10","dep_nom":"Aube","dep_slug":"aube","reg_code":"44","reg_nom":"Grand Est","reg_slug":"grand-est"},"departement":{"code":"10","nom":"Aube","slug":"aube"},"region":{"code":"44","nom":"Grand Est","slug":"grand-est"},"villes_proches":[{"id":12528,"code_insee":"10040","nom_standard":"Bernon","nom_a":null,"nom_de":null,"slug_ville":"bernon","departement_id":0,"code_postal":"10130","population":160,"superficie_km2":"1798.93","latitude_centre":"47.9862","longitude_centre":"3.9902","distance_km":3.06},{"id":0,"code_insee":"10227","nom_standard":"Marolles-sous-Lignières","nom_a":null,"nom_de":null,"slug_ville":"marolles-sous-lignieres","departement_id":0,"code_postal":"10130","population":371,"superficie_km2":"1512.59","latitude_centre":"47.9602","longitude_centre":"3.9186","distance_km":3.62},{"id":0,"code_insee":"89423","nom_standard":"Tronchoy","nom_a":null,"nom_de":null,"slug_ville":"tronchoy","departement_id":0,"code_postal":"89700","population":119,"superficie_km2":"658.65","latitude_centre":"47.9234","longitude_centre":"3.9497","distance_km":4.64},{"id":12591,"code_insee":"10112","nom_standard":"Coussegrey","nom_a":null,"nom_de":null,"slug_ville":"coussegrey","departement_id":0,"code_postal":"10210","population":180,"superficie_km2":"1592.77","latitude_centre":"47.9511","longitude_centre":"4.0326","distance_km":5.08},{"id":0,"code_insee":"89098","nom_standard":"Cheney","nom_a":null,"nom_de":null,"slug_ville":"cheney","departement_id":0,"code_postal":"89700","population":235,"superficie_km2":"598.06","latitude_centre":"47.9152","longitude_centre":"3.9591","distance_km":5.4},{"id":12579,"code_insee":"10099","nom_standard":"Chessy-les-Prés","nom_a":null,"nom_de":null,"slug_ville":"chessy-les-pres","departement_id":0,"code_postal":"10130","population":534,"superficie_km2":"2573.19","latitude_centre":"48.013","longitude_centre":"3.9345","distance_km":6.01},{"id":0,"code_insee":"10309","nom_standard":"Prusy","nom_a":null,"nom_de":null,"slug_ville":"prusy","departement_id":0,"code_postal":"10210","population":84,"superficie_km2":"396.45","latitude_centre":"47.9744","longitude_centre":"4.0529","distance_km":6.51},{"id":0,"code_insee":"89169","nom_standard":"Flogny-la-Chapelle","nom_a":null,"nom_de":null,"slug_ville":"flogny-la-chapelle","departement_id":0,"code_postal":"89360","population":935,"superficie_km2":"2379.03","latitude_centre":"47.9621","longitude_centre":"3.8786","distance_km":6.58},{"id":0,"code_insee":"10395","nom_standard":"Vanlay","nom_a":null,"nom_de":null,"slug_ville":"vanlay","departement_id":0,"code_postal":"10210","population":284,"superficie_km2":"2593.61","latitude_centre":"48.0176","longitude_centre":"4.0129","distance_km":6.92},{"id":0,"code_insee":"89323","nom_standard":"Roffey","nom_a":null,"nom_de":null,"slug_ville":"roffey","departement_id":0,"code_postal":"89700","population":148,"superficie_km2":"866.75","latitude_centre":"47.91","longitude_centre":"3.9122","distance_km":7.21},{"id":0,"code_insee":"89137","nom_standard":"Dannemoine","nom_a":null,"nom_de":null,"slug_ville":"dannemoine","departement_id":0,"code_postal":"89700","population":452,"superficie_km2":"1025.84","latitude_centre":"47.8978","longitude_centre":"3.9818","distance_km":7.39},{"id":0,"code_insee":"10394","nom_standard":"Vallières","nom_a":null,"nom_de":null,"slug_ville":"vallieres","departement_id":0,"code_postal":"10210","population":167,"superficie_km2":"836.62","latitude_centre":"47.9988","longitude_centre":"4.0601","distance_km":7.96},{"id":12568,"code_insee":"10087","nom_standard":"Chaserey","nom_a":null,"nom_de":null,"slug_ville":"chaserey","departement_id":0,"code_postal":"10210","population":45,"superficie_km2":"692.99","latitude_centre":"47.9534","longitude_centre":"4.0743","distance_km":8.07},{"id":0,"code_insee":"89447","nom_standard":"Vézinnes","nom_a":null,"nom_de":null,"slug_ville":"vezinnes","departement_id":0,"code_postal":"89700","population":158,"superficie_km2":"626.10","latitude_centre":"47.894","longitude_centre":"3.9342","distance_km":8.11},{"id":0,"code_insee":"89262","nom_standard":"Molosmes","nom_a":null,"nom_de":null,"slug_ville":"molosmes","departement_id":0,"code_postal":"89700","population":155,"superficie_km2":"2461.67","latitude_centre":"47.9021","longitude_centre":"4.0279","distance_km":8.2},{"id":0,"code_insee":"89038","nom_standard":"Bernouil","nom_a":null,"nom_de":null,"slug_ville":"bernouil","departement_id":0,"code_postal":"89360","population":109,"superficie_km2":"458.71","latitude_centre":"47.9049","longitude_centre":"3.8974","distance_km":8.33},{"id":12600,"code_insee":"10122","nom_standard":"Davrey","nom_a":null,"nom_de":null,"slug_ville":"davrey","departement_id":0,"code_postal":"10130","population":229,"superficie_km2":"961.54","latitude_centre":"48.0455","longitude_centre":"3.9555","distance_km":9.16},{"id":0,"code_insee":"89153","nom_standard":"Épineuil","nom_a":null,"nom_de":null,"slug_ville":"epineuil","departement_id":0,"code_postal":"89700","population":508,"superficie_km2":"619.60","latitude_centre":"47.8809","longitude_centre":"3.9907","distance_km":9.35},{"id":0,"code_insee":"89211","nom_standard":"Junay","nom_a":null,"nom_de":null,"slug_ville":"junay","departement_id":0,"code_postal":"89700","population":61,"superficie_km2":"362.47","latitude_centre":"47.8802","longitude_centre":"3.9395","distance_km":9.49},{"id":12516,"code_insee":"10024","nom_standard":"Avreuil","nom_a":null,"nom_de":null,"slug_ville":"avreuil","departement_id":0,"code_postal":"10130","population":167,"superficie_km2":"1034.10","latitude_centre":"48.054","longitude_centre":"3.9986","distance_km":10.33}]}