{"ville":{"id":8021,"code_insee":"76499","nom_standard":"Petiville","nom_a":null,"nom_de":null,"slug_ville":"petiville","departement_id":677,"code_postal":"76330","population":1142,"superficie_km2":"17.00","latitude_centre":"49.4539986","longitude_centre":"0.5840000","dep_code":"76","dep_nom":"Seine-Maritime","dep_slug":"seine-maritime","reg_code":"14","reg_nom":"Normandie","reg_slug":"normandie"},"departement":{"code":"76","nom":"Seine-Maritime","slug":"seine-maritime"},"region":{"code":"14","nom":"Normandie","slug":"normandie"},"villes_proches":[{"id":8013,"code_insee":"76476","nom_standard":"Port-Jérôme-sur-Seine","nom_a":null,"nom_de":null,"slug_ville":"port-jerome-sur-seine","departement_id":677,"code_postal":"76170","population":10387,"superficie_km2":"19.00","latitude_centre":"49.4900017","longitude_centre":"0.5730000","distance_km":4.08},{"id":7986,"code_insee":"76384","nom_standard":"Lillebonne","nom_a":null,"nom_de":null,"slug_ville":"lillebonne","departement_id":677,"code_postal":"76170","population":8729,"superficie_km2":"15.00","latitude_centre":"49.5089989","longitude_centre":"0.5340000","distance_km":7.1},{"id":8080,"code_insee":"76727","nom_standard":"Vatteville-la-Rue","nom_a":null,"nom_de":null,"slug_ville":"vatteville-la-rue","departement_id":677,"code_postal":"76940","population":1133,"superficie_km2":"49.00","latitude_centre":"49.4539986","longitude_centre":"0.6840000","distance_km":7.23},{"id":2015,"code_insee":"27107","nom_standard":"Bourneville-Sainte-Croix","nom_a":null,"nom_de":null,"slug_ville":"bourneville-sainte-croix","departement_id":628,"code_postal":"27500","population":1343,"superficie_km2":"11.00","latitude_centre":"49.3919983","longitude_centre":"0.6200000","distance_km":7.37},{"id":7960,"code_insee":"76281","nom_standard":"La Frénaye","nom_a":null,"nom_de":null,"slug_ville":"la-frenaye","departement_id":677,"code_postal":"76170","population":2081,"superficie_km2":"10.00","latitude_centre":"49.5209999","longitude_centre":"0.5740000","distance_km":7.49},{"id":2046,"code_insee":"27263","nom_standard":"Le Perrey","nom_a":null,"nom_de":null,"slug_ville":"le-perrey","departement_id":628,"code_postal":"27680","population":1229,"superficie_km2":"10.00","latitude_centre":"49.3779984","longitude_centre":"0.5740000","distance_km":8.48},{"id":8072,"code_insee":"76684","nom_standard":"Tancarville","nom_a":null,"nom_de":null,"slug_ville":"tancarville","departement_id":677,"code_postal":"76430","population":1218,"superficie_km2":"7.00","latitude_centre":"49.4809990","longitude_centre":"0.4520000","distance_km":10},{"id":8058,"code_insee":"76627","nom_standard":"Saint-Nicolas-de-la-Taille","nom_a":null,"nom_de":null,"slug_ville":"saint-nicolas-de-la-taille","departement_id":677,"code_postal":"76170","population":1642,"superficie_km2":"9.00","latitude_centre":"49.5139999","longitude_centre":"0.4700000","distance_km":10.6},{"id":2069,"code_insee":"27385","nom_standard":"Manneville-sur-Risle","nom_a":null,"nom_de":null,"slug_ville":"manneville-sur-risle","departement_id":628,"code_postal":"27500","population":1456,"superficie_km2":"9.00","latitude_centre":"49.3610001","longitude_centre":"0.5460000","distance_km":10.7},{"id":8036,"code_insee":"76557","nom_standard":"Saint-Arnoult","nom_a":null,"nom_de":null,"slug_ville":"saint-arnoult","departement_id":677,"code_postal":"76490","population":1453,"superficie_km2":"14.00","latitude_centre":"49.5369988","longitude_centre":"0.6770000","distance_km":11.41},{"id":7974,"code_insee":"76329","nom_standard":"Gruchet-le-Valasse","nom_a":null,"nom_de":null,"slug_ville":"gruchet-le-valasse","departement_id":677,"code_postal":"76210","population":3074,"superficie_km2":"14.00","latitude_centre":"49.5499992","longitude_centre":"0.5140000","distance_km":11.81},{"id":8035,"code_insee":"76556","nom_standard":"Saint-Antoine-la-Forêt","nom_a":null,"nom_de":null,"slug_ville":"saint-antoine-la-foret","departement_id":677,"code_postal":"76170","population":1097,"superficie_km2":"6.00","latitude_centre":"49.5390015","longitude_centre":"0.4810000","distance_km":12.03},{"id":7992,"code_insee":"76401","nom_standard":"Arelaune-en-Seine","nom_a":null,"nom_de":null,"slug_ville":"arelaune-en-seine","departement_id":677,"code_postal":"76940","population":2518,"superficie_km2":"45.00","latitude_centre":"49.4459992","longitude_centre":"0.7540000","distance_km":12.32},{"id":2084,"code_insee":"27467","nom_standard":"Pont-Audemer","nom_a":null,"nom_de":null,"slug_ville":"pont-audemer","departement_id":628,"code_postal":"27500","population":9848,"superficie_km2":"10.00","latitude_centre":"49.3460007","longitude_centre":"0.5340000","distance_km":12.54},{"id":2029,"code_insee":"27174","nom_standard":"Corneville-sur-Risle","nom_a":null,"nom_de":null,"slug_ville":"corneville-sur-risle","departement_id":628,"code_postal":"27500","population":1374,"superficie_km2":"13.00","latitude_centre":"49.3409996","longitude_centre":"0.5980000","distance_km":12.61},{"id":7933,"code_insee":"76169","nom_standard":"La Cerlangue","nom_a":null,"nom_de":null,"slug_ville":"la-cerlangue","departement_id":677,"code_postal":"76430","population":1297,"superficie_km2":"29.00","latitude_centre":"49.4879990","longitude_centre":"0.4160000","distance_km":12.71},{"id":2090,"code_insee":"27500","nom_standard":"Routot","nom_a":null,"nom_de":null,"slug_ville":"routot","departement_id":628,"code_postal":"27350","population":1670,"superficie_km2":"7.00","latitude_centre":"49.3849983","longitude_centre":"0.7260000","distance_km":12.82},{"id":7930,"code_insee":"76164","nom_standard":"Rives-en-Seine","nom_a":null,"nom_de":null,"slug_ville":"rives-en-seine","departement_id":677,"code_postal":"76490","population":4078,"superficie_km2":"5.00","latitude_centre":"49.5299988","longitude_centre":"0.7350000","distance_km":13.8},{"id":2111,"code_insee":"27656","nom_standard":"Toutainville","nom_a":null,"nom_de":null,"slug_ville":"toutainville","departement_id":628,"code_postal":"27500","population":1290,"superficie_km2":"12.00","latitude_centre":"49.3569984","longitude_centre":"0.4590000","distance_km":14.08},{"id":7998,"code_insee":"76418","nom_standard":"Maulévrier-Sainte-Gertrude","nom_a":null,"nom_de":null,"slug_ville":"maulevrier-sainte-gertrude","departement_id":677,"code_postal":"76490","population":1035,"superficie_km2":"14.00","latitude_centre":"49.5550003","longitude_centre":"0.7080000","distance_km":14.36}]}