{"ville":{"id":21762,"code_insee":"42241","nom_standard":"Saint-Jodard","nom_a":null,"nom_de":null,"slug_ville":"saint-jodard","departement_id":0,"code_postal":"42590","population":393,"superficie_km2":"671.27","latitude_centre":"45.8887","longitude_centre":"4.1294","dep_code":"42","dep_nom":"Loire","dep_slug":"loire","reg_code":"84","reg_nom":"Auvergne-Rhône-Alpes","reg_slug":"auvergne-rhone-alpes"},"departement":{"code":"42","nom":"Loire","slug":"loire"},"region":{"code":"84","nom":"Auvergne-Rhône-Alpes","slug":"auvergne-rhone-alpes"},"villes_proches":[{"id":21730,"code_insee":"42171","nom_standard":"Pinay","nom_a":null,"nom_de":null,"slug_ville":"pinay","departement_id":0,"code_postal":"42590","population":286,"superficie_km2":"666.23","latitude_centre":"45.8707","longitude_centre":"4.1307","distance_km":2.0},{"id":0,"code_insee":"42156","nom_standard":"Neulise","nom_a":null,"nom_de":null,"slug_ville":"neulise","departement_id":0,"code_postal":"42590","population":1344,"superficie_km2":"2305.18","latitude_centre":"45.9037","longitude_centre":"4.1681","distance_km":3.43},{"id":0,"code_insee":"42277","nom_standard":"Saint-Priest-la-Roche","nom_a":null,"nom_de":null,"slug_ville":"saint-priest-la-roche","departement_id":0,"code_postal":"42590","population":341,"superficie_km2":"1358.86","latitude_centre":"45.9204","longitude_centre":"4.1085","distance_km":3.88},{"id":21753,"code_insee":"42226","nom_standard":"Saint-Georges-de-Baroille","nom_a":null,"nom_de":null,"slug_ville":"saint-georges-de-baroille","departement_id":0,"code_postal":"42510","population":460,"superficie_km2":"1539.70","latitude_centre":"45.8513","longitude_centre":"4.1027","distance_km":4.64},{"id":0,"code_insee":"42254","nom_standard":"Saint-Marcel-de-Félines","nom_a":null,"nom_de":null,"slug_ville":"saint-marcel-de-felines","departement_id":0,"code_postal":"42122","population":827,"superficie_km2":"2249.81","latitude_centre":"45.8635","longitude_centre":"4.1824","distance_km":4.97},{"id":0,"code_insee":"42325","nom_standard":"Vendranges","nom_a":null,"nom_de":null,"slug_ville":"vendranges","departement_id":0,"code_postal":"42590","population":390,"superficie_km2":"1113.07","latitude_centre":"45.9344","longitude_centre":"4.1329","distance_km":5.09},{"id":0,"code_insee":"42268","nom_standard":"Vézelin-sur-Loire","nom_a":null,"nom_de":null,"slug_ville":"vezelin-sur-loire","departement_id":0,"code_postal":"42260","population":811,"superficie_km2":"3966.32","latitude_centre":"45.8858","longitude_centre":"4.0578","distance_km":5.55},{"id":21675,"code_insee":"42077","nom_standard":"Croizet-sur-Gand","nom_a":null,"nom_de":null,"slug_ville":"croizet-sur-gand","departement_id":0,"code_postal":"42540","population":320,"superficie_km2":"599.96","latitude_centre":"45.9104","longitude_centre":"4.2188","distance_km":7.33},{"id":21731,"code_insee":"42173","nom_standard":"Pommiers-en-Forez","nom_a":null,"nom_de":null,"slug_ville":"pommiers-en-forez","departement_id":0,"code_postal":"42260","population":378,"superficie_km2":"2420.84","latitude_centre":"45.8327","longitude_centre":"4.0785","distance_km":7.37},{"id":0,"code_insee":"42011","nom_standard":"Balbigny","nom_a":null,"nom_de":null,"slug_ville":"balbigny","departement_id":0,"code_postal":"42510","population":2911,"superficie_km2":"1700.32","latitude_centre":"45.8299","longitude_centre":"4.1813","distance_km":7.67},{"id":21672,"code_insee":"42070","nom_standard":"Cordelle","nom_a":null,"nom_de":null,"slug_ville":"cordelle","departement_id":0,"code_postal":"42123","population":941,"superficie_km2":"2666.87","latitude_centre":"45.9404","longitude_centre":"4.059","distance_km":7.92},{"id":0,"code_insee":"42212","nom_standard":"Saint-Cyr-de-Favières","nom_a":null,"nom_de":null,"slug_ville":"saint-cyr-de-favieres","departement_id":0,"code_postal":"42123","population":1037,"superficie_km2":"1424.68","latitude_centre":"45.959","longitude_centre":"4.1018","distance_km":8.1},{"id":21721,"code_insee":"42153","nom_standard":"Neaux","nom_a":null,"nom_de":null,"slug_ville":"neaux","departement_id":0,"code_postal":"42470","population":485,"superficie_km2":"1749.65","latitude_centre":"45.9583","longitude_centre":"4.1636","distance_km":8.18},{"id":0,"code_insee":"42155","nom_standard":"Nervieux","nom_a":null,"nom_de":null,"slug_ville":"nervieux","departement_id":0,"code_postal":"42510","population":1040,"superficie_km2":"1966.45","latitude_centre":"45.8121","longitude_centre":"4.1475","distance_km":8.63},{"id":21722,"code_insee":"42154","nom_standard":"Néronde","nom_a":null,"nom_de":null,"slug_ville":"neronde","departement_id":0,"code_postal":"42510","population":484,"superficie_km2":"858.85","latitude_centre":"45.8392","longitude_centre":"4.233","distance_km":9.73},{"id":0,"code_insee":"42289","nom_standard":"Saint-Symphorien-de-Lay","nom_a":null,"nom_de":null,"slug_ville":"saint-symphorien-de-lay","departement_id":0,"code_postal":"42470","population":1979,"superficie_km2":"3274.38","latitude_centre":"45.9474","longitude_centre":"4.223","distance_km":9.75},{"id":21726,"code_insee":"42161","nom_standard":"Notre-Dame-de-Boisset","nom_a":null,"nom_de":null,"slug_ville":"notre-dame-de-boisset","departement_id":0,"code_postal":"42120","population":571,"superficie_km2":"908.37","latitude_centre":"45.9896","longitude_centre":"4.1325","distance_km":11.22},{"id":21716,"code_insee":"42143","nom_standard":"Mizérieux","nom_a":null,"nom_de":null,"slug_ville":"mizerieux","departement_id":0,"code_postal":"42110","population":538,"superficie_km2":"706.31","latitude_centre":"45.7905","longitude_centre":"4.1646","distance_km":11.25},{"id":21728,"code_insee":"42166","nom_standard":"Parigny","nom_a":null,"nom_de":null,"slug_ville":"parigny","departement_id":0,"code_postal":"42120","population":629,"superficie_km2":"920.34","latitude_centre":"45.9892","longitude_centre":"4.093","distance_km":11.52},{"id":21752,"code_insee":"42221","nom_standard":"Sainte-Foy-Saint-Sulpice","nom_a":null,"nom_de":null,"slug_ville":"sainte-foy-saint-sulpice","departement_id":0,"code_postal":"42110","population":568,"superficie_km2":"2936.20","latitude_centre":"45.7759","longitude_centre":"4.1086","distance_km":12.65}]}