{"ville":{"id":15162,"code_insee":"19279","nom_standard":"Vars-sur-Roseix","nom_a":null,"nom_de":null,"slug_ville":"vars-sur-roseix","departement_id":0,"code_postal":"19130","population":415,"superficie_km2":"441.68","latitude_centre":"45.2625","longitude_centre":"1.3741","dep_code":"19","dep_nom":"Corrèze","dep_slug":"correze","reg_code":"75","reg_nom":"Nouvelle-Aquitaine","reg_slug":"nouvelle-aquitaine"},"departement":{"code":"19","nom":"Corrèze","slug":"correze"},"region":{"code":"75","nom":"Nouvelle-Aquitaine","slug":"nouvelle-aquitaine"},"villes_proches":[{"id":15099,"code_insee":"19195","nom_standard":"Saint-Cyprien","nom_a":null,"nom_de":null,"slug_ville":"saint-cyprien","departement_id":0,"code_postal":"19130","population":377,"superficie_km2":"773.88","latitude_centre":"45.2534","longitude_centre":"1.3638","distance_km":1.29},{"id":15100,"code_insee":"19196","nom_standard":"Saint-Cyr-la-Roche","nom_a":null,"nom_de":null,"slug_ville":"saint-cyr-la-roche","departement_id":0,"code_postal":"19130","population":450,"superficie_km2":"841.38","latitude_centre":"45.2783","longitude_centre":"1.384","distance_km":1.92},{"id":15089,"code_insee":"19182","nom_standard":"Saint-Aulaire","nom_a":null,"nom_de":null,"slug_ville":"saint-aulaire","departement_id":0,"code_postal":"19130","population":773,"superficie_km2":"1100.07","latitude_centre":"45.237","longitude_centre":"1.3889","distance_km":3.06},{"id":0,"code_insee":"19153","nom_standard":"Objat","nom_a":null,"nom_de":null,"slug_ville":"objat","departement_id":0,"code_postal":"19130","population":3721,"superficie_km2":"959.74","latitude_centre":"45.266","longitude_centre":"1.4153","distance_km":3.25},{"id":15092,"code_insee":"19187","nom_standard":"Saint-Bonnet-la-Rivière","nom_a":null,"nom_de":null,"slug_ville":"saint-bonnet-la-riviere","departement_id":0,"code_postal":"19130","population":389,"superficie_km2":"1009.87","latitude_centre":"45.2953","longitude_centre":"1.3582","distance_km":3.85},{"id":14953,"code_insee":"19015","nom_standard":"Ayen","nom_a":null,"nom_de":null,"slug_ville":"ayen","departement_id":0,"code_postal":"19310","population":717,"superficie_km2":"1336.43","latitude_centre":"45.2541","longitude_centre":"1.325","distance_km":3.96},{"id":15134,"code_insee":"19242","nom_standard":"Saint-Solve","nom_a":null,"nom_de":null,"slug_ville":"saint-solve","departement_id":0,"code_postal":"19130","population":450,"superficie_km2":"593.42","latitude_centre":"45.3074","longitude_centre":"1.4014","distance_km":5.43},{"id":14968,"code_insee":"19035","nom_standard":"Chabrignac","nom_a":null,"nom_de":null,"slug_ville":"chabrignac","departement_id":0,"code_postal":"19350","population":542,"superficie_km2":"1099.98","latitude_centre":"45.3124","longitude_centre":"1.3427","distance_km":6.07},{"id":0,"code_insee":"19288","nom_standard":"Voutezac","nom_a":null,"nom_de":null,"slug_ville":"voutezac","departement_id":0,"code_postal":"19130","population":1249,"superficie_km2":"2199.62","latitude_centre":"45.291","longitude_centre":"1.4428","distance_km":6.24},{"id":15131,"code_insee":"19239","nom_standard":"Saint-Robert","nom_a":null,"nom_de":null,"slug_ville":"saint-robert","departement_id":0,"code_postal":"19310","population":294,"superficie_km2":"612.83","latitude_centre":"45.2543","longitude_centre":"1.2945","distance_km":6.3},{"id":15084,"code_insee":"19177","nom_standard":"Rosiers-de-Juillac","nom_a":null,"nom_de":null,"slug_ville":"rosiers-de-juillac","departement_id":0,"code_postal":"19350","population":177,"superficie_km2":"962.41","latitude_centre":"45.2889","longitude_centre":"1.3018","distance_km":6.37},{"id":15070,"code_insee":"19161","nom_standard":"Perpezac-le-Blanc","nom_a":null,"nom_de":null,"slug_ville":"perpezac-le-blanc","departement_id":0,"code_postal":"19310","population":427,"superficie_km2":"1890.41","latitude_centre":"45.2147","longitude_centre":"1.3231","distance_km":6.65},{"id":0,"code_insee":"19289","nom_standard":"Yssandon","nom_a":null,"nom_de":null,"slug_ville":"yssandon","departement_id":0,"code_postal":"19310","population":696,"superficie_km2":"1964.23","latitude_centre":"45.2024","longitude_centre":"1.3849","distance_km":6.74},{"id":0,"code_insee":"19005","nom_standard":"Allassac","nom_a":null,"nom_de":null,"slug_ville":"allassac","departement_id":0,"code_postal":"19240","population":4081,"superficie_km2":"3885.96","latitude_centre":"45.2573","longitude_centre":"1.4609","distance_km":6.82},{"id":0,"code_insee":"19286","nom_standard":"Vignols","nom_a":null,"nom_de":null,"slug_ville":"vignols","departement_id":0,"code_postal":"19130","population":536,"superficie_km2":"1520.44","latitude_centre":"45.3252","longitude_centre":"1.4047","distance_km":7.37},{"id":15027,"code_insee":"19109","nom_standard":"Lascaux","nom_a":null,"nom_de":null,"slug_ville":"lascaux","departement_id":0,"code_postal":"19130","population":228,"superficie_km2":"742.53","latitude_centre":"45.3389","longitude_centre":"1.3734","distance_km":8.5},{"id":0,"code_insee":"19278","nom_standard":"Varetz","nom_a":null,"nom_de":null,"slug_ville":"varetz","departement_id":0,"code_postal":"19240","population":2409,"superficie_km2":"2051.53","latitude_centre":"45.1914","longitude_centre":"1.4365","distance_km":9.29},{"id":0,"code_insee":"19094","nom_standard":"Juillac","nom_a":null,"nom_de":null,"slug_ville":"juillac","departement_id":0,"code_postal":"19350","population":1153,"superficie_km2":"3258.84","latitude_centre":"45.3253","longitude_centre":"1.2897","distance_km":9.61},{"id":14965,"code_insee":"19030","nom_standard":"Brignac-la-Plaine","nom_a":null,"nom_de":null,"slug_ville":"brignac-la-plaine","departement_id":0,"code_postal":"19310","population":977,"superficie_km2":"1885.80","latitude_centre":"45.1745","longitude_centre":"1.3234","distance_km":10.56},{"id":0,"code_insee":"19124","nom_standard":"Mansac","nom_a":null,"nom_de":null,"slug_ville":"mansac","departement_id":0,"code_postal":"19520","population":1554,"superficie_km2":"1879.75","latitude_centre":"45.1584","longitude_centre":"1.3832","distance_km":11.6}]}